aws_cdk/cli_lib_alpha/__init__.py
aws_cdk/cli_lib_alpha/py.typed
aws_cdk/cli_lib_alpha/_jsii/__init__.py
aws_cdk/cli_lib_alpha/_jsii/cli-lib-alpha@3.0.0-alpha.0.jsii.tgz
aws_cdk_cli_lib_alpha-3.0.0a0.dist-info/LICENSE
aws_cdk_cli_lib_alpha-3.0.0a0.dist-info/METADATA
aws_cdk_cli_lib_alpha-3.0.0a0.dist-info/NOTICE
aws_cdk_cli_lib_alpha-3.0.0a0.dist-info/WHEEL
aws_cdk_cli_lib_alpha-3.0.0a0.dist-info/top_level.txt
aws_cdk_cli_lib_alpha-3.0.0a0.dist-info/RECORD
