Metadata-Version: 2.1
Name: aws-cdk.cli-lib-alpha
Version: 3.0.0a0
Summary: AWS CDK Programmatic CLI library
Home-page: https://github.com/aws/aws-cdk
Author: Amazon Web Services
License: Apache-2.0
Project-URL: Source, https://github.com/aws/aws-cdk-cli
Classifier: Intended Audience :: Developers
Classifier: Operating System :: OS Independent
Classifier: Programming Language :: JavaScript
Classifier: Programming Language :: Python :: 3 :: Only
Classifier: Programming Language :: Python :: 3.9
Classifier: Programming Language :: Python :: 3.10
Classifier: Programming Language :: Python :: 3.11
Classifier: Typing :: Typed
Classifier: Development Status :: 4 - Beta
Classifier: License :: OSI Approved
Classifier: Framework :: AWS CDK
Classifier: Framework :: AWS CDK :: 2
Requires-Python: ~=3.9
License-File: LICENSE
License-File: NOTICE
Requires-Dist: jsii<2.0.0,>=1.111.0
Requires-Dist: publication>=0.0.3
Requires-Dist: typeguard<4.3.0,>=2.13.3
